[
  {
    "id": "mnhoq5xsqd7k44m8tp",
    "company": "Biocodex",
    "position": "Alternant(e) Technicien Support Informatique - Tous genres",
    "date": "2026-04-02",
    "source": "Indeed",
    "status": "envoye",
    "link": "https://to.indeed.com/aa4kkh2sdnzr",
    "notes": "",
    "coverLetter": "Madame, Monsieur,\n\nActuellement en deuxième année de BTS SIO option SISR au CFA UTEC, je recherche un contrat d'apprentissage pour préparer ma Licence Générale Informatique spécialité Cybersécurité. Votre offre d'alternance pour le poste de Technicien Support Informatique au sein du siège de Biocodex à Gentilly a retenu mon attention.\n\nAssurer le support de niveau 1 et 2 auprès des utilisateurs, administrer et dépanner les postes de travail sous Windows 11, gérer les comptes Active Directory et les droits associés, et contribuer à des projets d'infrastructure — ce sont précisément les missions pour lesquelles ma formation en BTS SIO SISR m'a préparé et que je pratique déjà dans le cadre de mes travaux pratiques et de mon stage.\n\nJe maîtrise l'administration des environnements Windows (10/11), la gestion des comptes et des politiques Active Directory, ainsi que l'utilisation de la suite Microsoft 365. Attentif aux utilisateurs, rigoureux et capable de documenter mes interventions, je suis également sensibilisé aux bonnes pratiques de sécurité des postes de travail (gestion des antivirus, mises à jour, contrôle des accès). Rejoindre une société pharmaceutique familiale à forte empreinte internationale comme Biocodex serait une expérience enrichissante pour développer mes compétences dans un environnement structuré et bienveillant.\n\nJe me tiens disponible pour un entretien à votre convenance à compter de septembre 2026.\n\nVeuillez agréer, Madame, Monsieur, l'expression de mes sincères salutations.\n\nOrchiller Florian\n0624074245 | florian.orchiller@gmail.com",
    "hrContacts": [
      {
        "name": "Katerina Houpert",
        "email": "",
        "linkedin": "https://fr.linkedin.com/in/katerina-houpert-ab81b37/fr"
      }
    ],
    "careerUrl": "https://to.indeed.com/aa4kkh2sdnzr",
    "location": "Gentilly (94) · ~35 km",
    "offerId": "biocodex-support-it-gentilly"
  },
  {
    "id": "mnhoq3spr0tjq9fydr",
    "company": "NRJ Audio (NRJ Group)",
    "position": "ALTERNANT Technicien Support Informatique H/F/NB",
    "date": "2026-04-02",
    "source": "Indeed",
    "status": "envoye",
    "link": "https://to.indeed.com/aag462vc7jpd",
    "notes": "",
    "coverLetter": "Madame, Monsieur,\n\nActuellement en deuxième année de BTS SIO option SISR au CFA UTEC, je recherche un contrat d'apprentissage pour préparer ma Licence Générale Informatique spécialité Cybersécurité. Votre offre d'alternance pour le poste de Technicien Support Informatique au sein de la Direction Informatique de NRJ Audio à Paris a retenu toute mon attention.\n\nAssurer l'assistance informatique de proximité auprès des utilisateurs des sites parisiens, préparer et dépanner les postes bureautiques, gérer les comptes Active Directory et les droits utilisateurs, créer des comptes de messagerie Exchange et gérer la flotte mobile — ce sont des missions pour lesquelles ma formation BTS SIO SISR me confère des compétences directement opérationnelles.\n\nJe maîtrise les environnements Windows (7, 10, 11), l'administration Active Directory (création de comptes, gestion des GPO, droits), l'utilisation d'outils de ticketing comme GLPI, et j'ai développé des notions de scripting PowerShell dans le cadre de mes travaux pratiques. Réactif, à l'écoute, et rigoureux dans mes interventions, je suis également à l'aise avec les outils de prise en main à distance pour le support des utilisateurs en région. Évoluer dans l'univers des médias audio au sein d'un groupe reconnu comme NRJ serait une expérience particulièrement stimulante.\n\nJe me tiens disponible pour un entretien à votre convenance.\n\nVeuillez agréer, Madame, Monsieur, l'expression de mes sincères salutations.\n\nOrchiller Florian\n0624074245 | florian.orchiller@gmail.com",
    "hrContacts": [
      {
        "name": "Nathalie Pinon",
        "email": "",
        "linkedin": "https://fr.linkedin.com/in/nathalie-pinon-77068812b"
      },
      {
        "name": "Lisardo F",
        "email": "",
        "linkedin": "https://fr.linkedin.com/in/lisardo-f-4306729/fr"
      }
    ],
    "careerUrl": "https://to.indeed.com/aag462vc7jpd",
    "location": "Paris 16e (75) · ~38 km",
    "offerId": "nrj-audio-support-it-paris"
  },
  {
    "id": "mnhohtbkdq9lle5s3sq",
    "company": "Crédit Agricole",
    "position": "Alternance – Support Utilisateurs & Habilitations F/H",
    "date": "2026-04-02",
    "source": "Indeed",
    "status": "envoye",
    "link": "https://to.indeed.com/aaypw4mnqxtr",
    "notes": "",
    "coverLetter": "Madame, Monsieur,\n\nActuellement en deuxième année de BTS SIO option SISR au CFA UTEC, je suis à la recherche d'un contrat d'apprentissage pour ma Licence Générale Informatique spécialité Cybersécurité. Votre offre d'alternance au sein du service Support et Habilitations du Crédit Agricole correspond à un domaine au croisement de l'assistance informatique et de la gestion des accès, deux axes essentiels de ma formation.\n\nLa gestion des habilitations et des droits d'accès est un pilier fondamental de la sécurité des systèmes d'information. Évoluer au sein d'un établissement bancaire de référence comme le Crédit Agricole me permettrait d'appréhender les enjeux réels de contrôle des accès, de conformité et de gouvernance des identités dans un contexte à forts impératifs de sécurité.\n\nMa formation en BTS SIO SISR m'a permis de développer des compétences en support utilisateur (niveaux 1 et 2), en gestion des comptes Active Directory, en administration des droits et politiques de groupe (GPO), ainsi qu'en sensibilisation des utilisateurs aux bonnes pratiques de sécurité. Je suis rigoureux, pédagogue et à l'aise dans la relation avec les utilisateurs.\n\nJe reste disponible pour un entretien à votre convenance.\n\nBien cordialement,\n\nOrchiller Florian\n0624074245 | florian.orchiller@gmail.com",
    "hrContacts": [
      {
        "name": "Osvaldo Pimentel",
        "email": "",
        "linkedin": "https://fr.linkedin.com/in/osvaldo-pimentel-55524a159"
      },
      {
        "name": "Nadir Bouledjeraf",
        "email": "",
        "linkedin": "https://fr.linkedin.com/in/nadir-bouledjeraf-974b6a172"
      }
    ],
    "careerUrl": "https://recrutement.ca-paris.fr/",
    "location": "Brunoy (91) · ~30 km",
    "offerId": "ca-support"
  },
  {
    "id": "mnhhhybo56ku6dercnr",
    "company": "Equans",
    "position": "Alternance – Ingénieur logiciel et SI F/H",
    "date": "2026-04-02",
    "source": "Indeed",
    "status": "envoye",
    "link": "https://to.indeed.com/aab7wkgzsm9n",
    "notes": ""
  },
  {
    "id": "mnhhghkz6z7qn648q56",
    "company": "VINCI Construction",
    "position": "Alternance – Technicien SI H/F",
    "date": "2026-04-02",
    "source": "Indeed",
    "status": "envoye",
    "link": "https://to.indeed.com/aa2fcdhbpzsg",
    "notes": ""
  },
  {
    "id": "mnda7bx463vm5gc6tzr",
    "company": "CNP Assurances",
    "position": "Alternance  Analyste Cybersécurité SOC/SIEM H/F (Licence)",
    "date": "2026-03-30",
    "source": "Site entreprise",
    "status": "envoye",
    "link": "https://to.indeed.com/aatvdpss2m7g",
    "notes": ""
  },
  {
    "id": "mncvpk4jyncbftbhrm9",
    "company": "Crédit Agricole",
    "position": "Alternance sécurité informatique SOC F/H",
    "date": "2026-03-30",
    "source": "Indeed",
    "status": "envoye",
    "link": "https://to.indeed.com/aamjdf4kp9bc",
    "notes": ""
  },
  {
    "id": "mnbz32lj65jme2c1qup",
    "company": "Crédit Agricole",
    "position": "Alternance Support Utilisateurs & Habilitations F/H",
    "date": "2026-03-29",
    "source": "Indeed",
    "status": "envoye",
    "link": "https://to.indeed.com/aaypw4mnqxtr",
    "notes": ""
  }
]